[
	{
		"game": "Dishonored: Death of the Outsider",
		"image": "https://www.speedrun.com/dishonored_doto"
	},
	{
		"title": "Hitless / Damageless / Clean Hands / No Upgrades",
		"video": "",
		"rules": "",
		"completed": true,
		"world_first": false
	},
	{
		"title": "Hitless / Damageless / Range Only / No Upgrades",
		"video": "",
		"rules": "",
		"completed": true,
		"world_first": true
	},
	{
		"title": "NG+ / Hitless / Damageless / Ghost / Clean Hands / No Upgrades",
		"video": "",
		"rules": "",
		"completed": true,
		"world_first": false
	},
	{
		"title": "NG+ / Hitless / Damageless / Range Only / No Upgrades",
		"video": "",
		"rules": "",
		"completed": true,
		"world_first": true
	},
	{
		"title": "Hitless / Damageless / Knife Only / No Upgrades / No HUD",
		"video": "",
		"rules": "",
		"completed": true,
		"world_first": true
	},
	{
		"title": "Hitless / Damageless / No Knockouts / No Upgrades / No HUD",
		"video": "",
		"rules": "",
		"completed": true,
		"world_first": true
	},
	{
		"title": "NG+ / Hitless / Damageless / Clean Hands / No Upgrades / No Weapons / No HUD",
		"video": "",
		"rules": "",
		"completed": true,
		"world_first": true
	},
	{
		"title": "NG & NG+ (Two Endings) / Hitless / Damageless / Knife Only / No Upgrades / No HUD",
		"video": "",
		"rules": "",
		"completed": true,
		"world_first": true
	},
	{
		"title": "NG+ / Hitless / Damageless / No Knockouts / Clean Hands / No Weapons / No Upgrades",
		"video": "",
		"rules": "",
		"completed": true,
		"world_first": true
	},
	{
		"title": "NG & NG+ / Hitless / Damageless / Ghost / Clean Hands / No Upgrades / No Weapons / No HUD",
		"video": "",
		"rules": "",
		"completed": true,
		"world_first": true
	},
	{
		"title": "Hitless / Damageless",
		"video": "",
		"rules": "",
		"completed": true,
		"world_first": false
	},
	{
		"title": "Hitless / Damageless / Ghost",
		"video": "",
		"rules": "",
		"completed": true,
		"world_first": false
	},
	{
		"title": "Hitless / Damageless / Knife Only / No Upgrades",
		"video": "",
		"rules": "",
		"completed": true,
		"world_first": false
	},
	{
		"title": "NG & NG+ (Two Endings) / Hitless / No Upgrades",
		"video": "",
		"rules": "",
		"completed": true,
		"world_first": true
	}
]
