[
	{
		"game": "Dishonored: The Brigmore Witches (DLC)",
		"speedrun_website": "https://www.speedrun.com/dishonored"
	},
	{
		"title": "Hitless / Ghost / Clean Hands / No Upgrades / Hands Only",
		"rules": "",
		"completed": true,
		"world_first": false
	},
	{
		"title": "Hitless / Damageless / Ghost / Knife Only / No Upgrades",
		"rules": "",
		"completed": true,
		"world_first": true
	},
	{
		"title": "Hitless / Damageless / Ghost / Clean Hands / No Upgrades / No Weapons / Hands Only",
		"rules": "",
		"completed": true,
		"world_first": false
	},
	{
		"title": "Hitless / Damageless / Ghost / Clean Hands / Range Only / No Upgrades",
		"rules": "",
		"completed": true,
		"world_first": true
	}
]